Metadata-Version: 2.1
Name: diergonn-lab_one
Version: 1.0.1
Summary: Project for learning gitlab ci
Author: David
Author-email: your@email.com
